{
  "book": "Johan-Masa",
  "chapter": 4,
  "sections": [
    {
      "sectionTitle": "Pasian' Kha leh Khrih' Galte",
      "reference": null,
      "verses": [
        {
          "verse": 1,
          "text": "Ka it lawmte aw, kha ka nei a ci mi khempeuh' thugen um kei un la, tua thute Pasian kiang pan mah ahi hiam, ci-in kantel un. Bang hang hiam cih leh leitungah kamsang a kineihkhem tampi hong om khinta hi"
        },
        {
          "verse": 2,
          "text": "Pasian' Kha sawlna tawh thugente leh adangte bangci khentheih ding na hi uh hiam cih leh: Jesuh Khrih pen mihing bangin hong pai hi, ci-in a gente khempeuh Pasian Kha' lamlahna tawh thugen ahi hi"
        },
        {
          "verse": 3,
          "text": "Ahi zongin hih thu a nial mi peuhmah, Pasian Kha' sawlna tawh thugen hilo uh hi. Hih bang mite pen Khrih' Gal hi a, hong paiding hi, ci-in na zaksa uh mah bangin tu-in leitungah a hong om khinta ahi uh hi"
        },
        {
          "verse": 4,
          "text": "Ka it tate aw, note, Pasian' mite na hi uh a, tua bang kamsang kineihkhemte a zokhin na hi uh hi. Bang hang hiam cih leh leitung mite a pan'pih dawimangpa sangin note hong ompih Pasian vanglian zaw hi"
        },
        {
          "verse": 5,
          "text": "Kamsang a kineihkhemte in leitung thu gen uh a, amaute pen Pasian a theilo hih leitung mite tawh kipawl uh ahih manin leitung mite in amau' thugen a ngai uh hi"
        },
        {
          "verse": 6,
          "text": "Ahi zongin note pen Pasian' mite na hi uh hi. Pasian a thei mi peuhmah in kote' thugen hong ngai uh a, Pasian' pawl a hilo mi peuhmah in kote' thugen hong ngailo uh hi. Tua ahih manin hih bangin thuman Kha leh zuau kha a kilamdan'na i theithei hi."
        }
      ]
    },
    {
      "sectionTitle": "Pasian, Ki-itna Hi",
      "reference": null,
      "verses": [
        {
          "verse": 7,
          "text": "Ka it lawmte aw, Pasian pen itna hong pian'khiatna bulpi ahih manin eite khatlekhat ki-it ni. Itna a nei mi peuhmah, Pasian' tate hi a, Pasian a thei uh hi"
        },
        {
          "verse": 8,
          "text": "Pasian pen ki-itna ahih manin itna a neilo mite in Pasian theilo uh hi"
        },
        {
          "verse": 9,
          "text": "Pasian in eite hong itna hong bangci lah hiam cih leh: Ama hangin eite in nuntakna i ngahtheihna dingin a Tapa neihsun Pasian in leitungah a hong paisak hi"
        },
        {
          "verse": 10,
          "text": "Hih ka gen itna pen eite in Pasian i itna thu hilo a, Pasian in eite hong itin, i mawhna a maitheihna dingin a Tapa a hong paisakna thu ahi hi"
        },
        {
          "verse": 11,
          "text": "Ka it lawmte aw, Pasian in tua zahta-in eite hong it ahih leh eite zong khatlekhat i ki-it ding a kilawm ahi hi"
        },
        {
          "verse": 12,
          "text": "Kuamah in Pasian mu ngeilo hi. Ahi zongin eite khatlekhat i ki-it leh eite tawh Pasian hong omkhawm a, ama itna eite lakah a cingtaakin a om ahi hi"
        },
        {
          "verse": 13,
          "text": "Pasian in eite tungah a hong piak Kha Siangtho hangin Pasian leh eite a omkhawm ihihna leh Pasian in eite hong ompih ahihna thu i thei hi"
        },
        {
          "verse": 14,
          "text": "Pa Pasian in leitung mite a honkhia dingin a Tapa a hong paisakna thu kote in thei-in midang kiangah genbelin ka nei uh hi"
        },
        {
          "verse": 15,
          "text": "Jesuh pen Pasian' Tapa hi, ci-in umin a sang mite, Pasian in ompih a, tua mite pen Pasian tawh a omkhawm ahi uh hi"
        },
        {
          "verse": 16,
          "text": "Tua hi a, Pasian in eite a hong itna thu, eite mahmah in thei-in i um hi. Pasian pen ki-itna hi a, itna a nei mite pen Pasian tawh omkhawm uh a, Pasian zong amaute tawh a omkhawm hi"
        },
        {
          "verse": 17,
          "text": "Thukhen Ni ciangin kisuan'na nei hetloin i omtheihna dingin eite in a cingtaak itna a nei ihi hi. Khrih mah bangin hih leitung i nuntakna-ah nungta-in gamta ihih manin tua bang kisuan'na a neilo ding ihi hi"
        },
        {
          "verse": 18,
          "text": "Itna nei lehang launa omlo a, itna cingtaak nei peuh lehang launa beimangta hi. Bang hang hiam cih leh launa i cih pen gimthuak ding kihtakna hi a, gimthuak ding a laute pen itna cingtaak a neilote ahi hi"
        },
        {
          "verse": 19,
          "text": "Pasian in eite hong it masa ahih manin eite in itna i nei thei hi"
        },
        {
          "verse": 20,
          "text": "Mi khatpeuh in, “Pasian ka it hi,” ci napi-in a Khristian mipihte a muhdah leh a zuaupi a gen ahi hi. Bang hang hiam cih leh a muhtheih a Khristian mipih a itlo mi in a muhtheihloh Pasian it theilo ding hi"
        },
        {
          "verse": 21,
          "text": "Khrih in eite tungah hong thupiakna in: Pasian a it mi in a Khristian mipihte zong it ding hi, cihna ahi hi."
        }
      ]
    }
  ]
}